cpptopy/__init__.py
cpptopy/__main__.py
cpptopy/cpptopy.py
autoCppToPy-0.0.1.dist-info/METADATA
autoCppToPy-0.0.1.dist-info/WHEEL
autoCppToPy-0.0.1.dist-info/top_level.txt
autoCppToPy-0.0.1.dist-info/RECORD
