Metadata-Version: 2.1
Name: autoCppToPy
Version: 0.0.1
Summary: 'Can\'t remember how to compile C++ code into a python module with pybind11? autoCppToPy is here to make it easier than ever!'
Home-page: https://github.com/cornusandu/CppToPy
Author: Sandu Bogdan
Author-email: bogdanelsandu@hotmail.com
Project-URL: Bug Tracker, https://github.com/cornusandu/CppToPy/issues
Project-URL: GitHub Repository, https://github.com/cornusandu/CppToPy
Classifier: Environment :: Console
Classifier: Intended Audience :: Developers
Classifier: Natural Language :: English
Classifier: Operating System :: OS Independent
Classifier: Programming Language :: Python
Classifier: Programming Language :: Python :: 3
Classifier: Programming Language :: Python :: 3 :: Only
Classifier: Programming Language :: Python :: Implementation
Classifier: Programming Language :: Python :: Implementation :: CPython
Classifier: Programming Language :: C++
Requires-Python: >=3.10
